[{"width":4,"height":5,"lines":["BEEY","RODE","DIVS","GPMP","PORE"],"wordbankId":"wordbank-v1","symbolPairs":[[1,1],[0,2],[1,2],[4,4],[2,1],[1,1],[4,3],[1,1],[3,3],[0,0]]},{"width":5,"height":5,"lines":["BUREH","LITCS","HALLU","CEUJM","WKISW"],"wordbankId":"wordbank-v1","symbolPairs":[[1,1],[2,1],[0,0],[3,1],[4,0],[2,0],[4,1],[2,0]]},{"width":5,"height":5,"lines":["ISLIA","PUESF","GAOUE","BOGND","LURES"],"wordbankId":"wordbank-v1","symbolPairs":[[1,3],[4,4],[1,3],[1,2],[4,4],[3,4],[3,4],[4,3],[2,2],[2,3]]},{"width":6,"height":5,"lines":["HATJPT","COVEAB","AEDARL","RLOONS","ESBHAA"],"wordbankId":"wordbank-v1","symbolPairs":[[0,3],[3,1],[1,3],[1,0],[1,3],[1,3],[3,2]]},{"width":6,"height":5,"lines":["HACING","VIRYGO","RETAVS","OCFOLI","ENRWPD"],"wordbankId":"wordbank-v1","symbolPairs":[[0,0],[1,0],[2,4],[4,4],[1,2],[2,0],[2,4],[3,1],[1,1],[3,3]]},{"width":7,"height":5,"lines":["HAOGYVD","FOGEIER","BLNTNJO","WIROGTD","MAARRER"],"wordbankId":"wordbank-v1","symbolPairs":[[4,3],[3,1],[0,4],[2,0],[0,0],[2,1],[0,0],[2,1],[1,1],[2,0]]},{"width":7,"height":5,"lines":["GONSMQU","DURGIAS","JEGKLER","SICWEON","PUOAGAC"],"wordbankId":"wordbank-v1","symbolPairs":[[2,1],[3,1],[4,1],[0,1],[1,3],[4,2],[4,2],[2,2],[1,2]]}]