[{"width":4,"height":5,"lines":["HODS","DAGE","WISH","CEAO","TZCA"],"wordbankId":"wordbank-v1","symbolPairs":[[0,2],[0,0],[2,1],[2,0],[2,2],[1,0],[0,0],[2,2],[3,3],[1,2]]},{"width":5,"height":5,"lines":["MAOAE","RISTY","CYXKS","LORED","HAWOU"],"wordbankId":"wordbank-v1","symbolPairs":[[3,2],[4,3],[3,2],[4,3],[0,2],[2,2],[2,3],[2,3],[1,1],[0,1]]},{"width":5,"height":5,"lines":["UIDTT","BNSER","AAGUL","WLORD","CHISE"],"wordbankId":"wordbank-v1","symbolPairs":[[3,2],[0,1],[4,4],[2,3],[4,3],[2,1],[1,2],[4,3],[3,4],[4,4]]},{"width":6,"height":5,"lines":["HANDVD","LUSHEM","NOYMPS","MNOFQC","IEFZAH"],"wordbankId":"wordbank-v1","symbolPairs":[[2,2],[1,2],[1,2],[1,0],[0,2],[0,0],[2,0],[1,4],[0,0]]},{"width":6,"height":5,"lines":["BURRED","PANTUG","ATAINE","SLPERS","EUHCXY"],"wordbankId":"wordbank-v1","symbolPairs":[[1,0],[0,0],[3,3],[1,0],[0,0],[3,2],[3,2],[0,1],[3,3],[2,2]]},{"width":7,"height":5,"lines":["NDFNOMQ","DAEHETS","LIGGLRO","WONETEP","MARNKIS"],"wordbankId":"wordbank-v1","symbolPairs":[[4,4],[0,1],[2,1],[3,4],[1,1],[4,1],[3,3],[1,4],[3,4]]},{"width":7,"height":5,"lines":["FALTRAM","WLEUZED","SHOETIS","OCIAYSC","IPPKRHX"],"wordbankId":"wordbank-v1","symbolPairs":[[1,1],[2,1],[0,1],[1,2],[1,1],[3,2],[1,2],[2,3]]}]