[{"width":4,"height":5,"lines":["ZVOS","DOCK","CUNE","FIVD","JAPZ"],"wordbankId":"wordbank-v1","symbolPairs":[[0,2],[0,0],[3,3],[2,1],[2,2],[3,1],[2,1],[4,1],[4,2],[1,2]]},{"width":5,"height":5,"lines":["RIVID","LVMEY","GARNT","TRICS","PWEEU"],"wordbankId":"wordbank-v1","symbolPairs":[[1,3],[3,0],[1,0],[3,3],[2,0],[4,2],[0,0],[3,3],[1,1],[3,2]]},{"width":5,"height":5,"lines":["FIJMY","BULKS","EABLL","GBSEU","ORUDD"],"wordbankId":"wordbank-v1","symbolPairs":[[1,2],[1,4],[0,1],[1,1],[1,1],[3,2],[0,0],[3,1],[2,4],[2,2]]},{"width":6,"height":5,"lines":["BUHINE","GEROLD","JOGGEN","NIFEOR","WDUZSU"],"wordbankId":"wordbank-v1","symbolPairs":[[1,1],[4,0],[0,1],[0,3],[2,1],[1,2],[1,0],[4,2],[2,1],[3,0]]},{"width":6,"height":5,"lines":["TAOGVE","GREOGY","MVIATC","SEWIRS","AQREET"],"wordbankId":"wordbank-v1","symbolPairs":[[3,3],[4,3],[0,0],[2,3],[1,3],[1,0],[0,1],[1,1],[3,0],[1,1]]},{"width":7,"height":5,"lines":["BERIAFS","NUMRRED","MANMIJO","EVTNBTR","UBOURED"],"wordbankId":"wordbank-v1","symbolPairs":[[2,0],[0,1],[1,0],[2,3],[0,0],[0,0],[0,1],[2,4]]},{"width":7,"height":5,"lines":["FLEEOWD","SNODTEN","RONAHTR","DUTCZIH","PIGRAPU"],"wordbankId":"wordbank-v1","symbolPairs":[[2,1],[4,2],[0,0],[0,2],[1,0],[4,0],[0,0],[3,3],[4,2],[0,2]]}]